resourceprovider/__init__.py
resourceprovider-1.0.2.dist-info/LICENSE
resourceprovider-1.0.2.dist-info/METADATA
resourceprovider-1.0.2.dist-info/WHEEL
resourceprovider-1.0.2.dist-info/top_level.txt
resourceprovider-1.0.2.dist-info/RECORD
