Metadata-Version: 2.1
Name: resourceprovider
Version: 1.0.2
Summary: Single Instance of Resource needed in Application
Home-page: https://github.com/PyOneers/resource-provider
Author: PyOneers
Author-email: sutharpanks.opensource@gmail.com
License: UNKNOWN
Platform: UNKNOWN
Classifier: Programming Language :: Python :: 3
Classifier: License :: OSI Approved :: MIT License
Classifier: Operating System :: OS Independent
Requires-Python: >=3.6
